{
    "last_updated": "2018-03-20 05:55:22.154713",
    "2001": {
        "ab": 692,
        "g": 157,
        "pa": 738
    },
    "2002": {
        "ab": 647,
        "g": 157,
        "pa": 728
    },
    "2003": {
        "ab": 679,
        "g": 159,
        "pa": 725
    },
    "2004": {
        "ab": 704,
        "g": 161,
        "pa": 762
    },
    "2005": {
        "ab": 679,
        "g": 162,
        "pa": 739
    },
    "2006": {
        "ab": 695,
        "g": 161,
        "pa": 752
    },
    "2007": {
        "ab": 678,
        "g": 161,
        "pa": 736
    },
    "2008": {
        "ab": 686,
        "g": 162,
        "pa": 749
    },
    "2009": {
        "ab": 639,
        "g": 146,
        "pa": 678
    },
    "2010": {
        "ab": 680,
        "g": 162,
        "pa": 732
    },
    "2011": {
        "ab": 677,
        "g": 161,
        "pa": 721
    },
    "2012": {
        "ab": 629,
        "g": 162,
        "pa": 663
    },
    "2013": {
        "ab": 520,
        "g": 150,
        "pa": 555
    },
    "2014": {
        "ab": 359,
        "g": 143,
        "pa": 385
    },
    "2015": {
        "ab": 398,
        "g": 153,
        "pa": 438
    },
    "2016": {
        "ab": 327,
        "g": 143,
        "pa": 365
    },
    "2017": {
        "ab": 196,
        "g": 136,
        "pa": 215
    }
}